dsbench.py
dsbench-0.1.1.dist-info/LICENSE
dsbench-0.1.1.dist-info/METADATA
dsbench-0.1.1.dist-info/WHEEL
dsbench-0.1.1.dist-info/RECORD
