Metadata-Version: 2.1
Name: dsbench
Version: 0.1.1
Summary: 
Author: DemonicSavage
Author-email: gabrielhuwe@gmail.com
Requires-Python: >=3.9,<4.0
Classifier: Programming Language :: Python :: 3
Classifier: Programming Language :: Python :: 3.9
Classifier: Programming Language :: Python :: 3.10
Classifier: Programming Language :: Python :: 3.11
Requires-Dist: tqdm (>=4.66.1,<5.0.0)
